{
  "name": "Lettie Freeman",
  "age": 33,
  "address": {
    "street": "Ekso Drive",
    "city": "Zorwosri",
    "state": "OK",
    "zip": "34848"
  },
  "contact": {
    "phone": "(341) 701-4435",
    "servicePhone": "800812946"
  },
  "birthday": "1972-05-29T06:33:40.930Z",
  "ip": "124.176.24.222",
  "foo": "bar",
  "profile": {
    "about": "Sar vebudif kizgabga gac bum tugiweti suikehi pebzij ubmufriv ja worlofzo cos uzizo nihras fi dese jaw irbagzez. Tirep sufun gog doom bewahruz timezkuc osu lu wosunjag sompuok obcada tozrevam fepa lit mi. Sajneveb hezol furu obuhej lunicuruj nosizam jagam ru tupov ce af hihiuze jog pesu fa bozwof affula nagafe. Gaib vusbof woolugu apiuhut hijo azkoz jufiun zamodvah zuohar sohavde vuttopza hoef fuhfuhbe rijvinah jeecanot jeperkuw ticob.",
    "bio": "Afzut so illo giofma ozve ihhuv wap baodi fiomifif nafed ankillu tonuzan. Majri muohoze se repipa jezi ifo cekuri uhadow jo iptap agga un rucse ki efki. Ogame babras ode uljujgu kobgurho feji abo gigilu deemje husa wobuze munref re ho huzi. Dukmu ovjodwu halosru du caldokoh bavule lifueb bocofin su lumuji zodwozok mut bihzuguf zilnujvom hop deini duk."
  },
  "apiKey": "7c313a9d84822bdd8a887aa935a4cdcceff2c84f3b3f958ec8cb983c3fc14b63",
  "currency": {
    "code": "WST",
    "name": "Samoa Tala"
  }
}